<?xml version="1.0" ?>
<annotation>
    <filename>img-00253.jpg</filename>
    <size>
        <width>2397</width>
        <height>3484</height>
        <depth>3</depth>
    </size>
    <object>
        <name>word</name>
        <bndbox>
            <xmin>951</xmin>
            <ymin>1117</ymin>
            <xmax>1326</xmax>
            <ymax>1293</ymax>
        </bndbox>
    </object>
    <object>
        <name>word</name>
        <bndbox>
            <xmin>684</xmin>
            <ymin>1391</ymin>
            <xmax>1705</xmax>
            <ymax>1529</ymax>
        </bndbox>
    </object>
    <object>
        <name>word</name>
        <bndbox>
            <xmin>1227</xmin>
            <ymin>1642</ymin>
            <xmax>1946</xmax>
            <ymax>1848</ymax>
        </bndbox>
    </object>
    <object>
        <name>word</name>
        <bndbox>
            <xmin>669</xmin>
            <ymin>1815</ymin>
            <xmax>1387</xmax>
            <ymax>1925</ymax>
        </bndbox>
    </object>
    <object>
        <name>word</name>
        <bndbox>
            <xmin>681</xmin>
            <ymin>2224</ymin>
            <xmax>1668</xmax>
            <ymax>2592</ymax>
        </bndbox>
    </object>
    <object>
        <name>word</name>
        <bndbox>
            <xmin>620</xmin>
            <ymin>2097</ymin>
            <xmax>1897</xmax>
            <ymax>2215</ymax>
        </bndbox>
    </object>
    <object>
        <name>word</name>
        <bndbox>
            <xmin>620</xmin>
            <ymin>2647</ymin>
            <xmax>1663</xmax>
            <ymax>3245</ymax>
        </bndbox>
    </object>
    <object>
        <name>word</name>
        <bndbox>
            <xmin>801</xmin>
            <ymin>556</ymin>
            <xmax>2088</xmax>
            <ymax>1019</ymax>
        </bndbox>
    </object>
    <object>
        <name>word</name>
        <bndbox>
            <xmin>743</xmin>
            <ymin>162</ymin>
            <xmax>1920</xmax>
            <ymax>283</ymax>
        </bndbox>
    </object>
    <object>
        <name>word</name>
        <bndbox>
            <xmin>742</xmin>
            <ymin>293</ymin>
            <xmax>1813</xmax>
            <ymax>545</ymax>
        </bndbox>
    </object>
</annotation>
