<?xml version="1.0" ?>
<annotation>
    <filename>img-00197.jpg</filename>
    <size>
        <width>2397</width>
        <height>3484</height>
        <depth>3</depth>
    </size>
    <object>
        <name>word</name>
        <bndbox>
            <xmin>592</xmin>
            <ymin>1356</ymin>
            <xmax>2099</xmax>
            <ymax>1814</ymax>
        </bndbox>
    </object>
    <object>
        <name>word</name>
        <bndbox>
            <xmin>1329</xmin>
            <ymin>1903</ymin>
            <xmax>1918</xmax>
            <ymax>2208</ymax>
        </bndbox>
    </object>
    <object>
        <name>word</name>
        <bndbox>
            <xmin>656</xmin>
            <ymin>1882</ymin>
            <xmax>1257</xmax>
            <ymax>2066</ymax>
        </bndbox>
    </object>
    <object>
        <name>word</name>
        <bndbox>
            <xmin>660</xmin>
            <ymin>966</ymin>
            <xmax>1230</xmax>
            <ymax>1347</ymax>
        </bndbox>
    </object>
    <object>
        <name>word</name>
        <bndbox>
            <xmin>553</xmin>
            <ymin>367</ymin>
            <xmax>1170</xmax>
            <ymax>891</ymax>
        </bndbox>
    </object>
    <object>
        <name>word</name>
        <bndbox>
            <xmin>836</xmin>
            <ymin>146</ymin>
            <xmax>1449</xmax>
            <ymax>365</ymax>
        </bndbox>
    </object>
</annotation>
