<?xml version="1.0" ?>
<annotation>
    <filename>1058.jpg</filename>
    <size>
        <width>832</width>
        <height>832</height>
        <depth>3</depth>
    </size>
    <object>
        <name>Char</name>
        <bndbox>
            <xmin>5.35</xmin>
            <ymin>324.18</ymin>
            <xmax>27.28</xmax>
            <ymax>414.3</ymax>
        </bndbox>
    </object>
    <object>
        <name>Char</name>
        <bndbox>
            <xmin>27.55</xmin>
            <ymin>349.41</ymin>
            <xmax>47.12</xmax>
            <ymax>380.8</ymax>
        </bndbox>
    </object>
    <object>
        <name>Char</name>
        <bndbox>
            <xmin>44.76</xmin>
            <ymin>349.8</ymin>
            <xmax>60.78</xmax>
            <ymax>381.86</ymax>
        </bndbox>
    </object>
    <object>
        <name>Char</name>
        <bndbox>
            <xmin>62.1</xmin>
            <ymin>349.28</ymin>
            <xmax>79.04</xmax>
            <ymax>383.96</ymax>
        </bndbox>
    </object>
    <object>
        <name>Char</name>
        <bndbox>
            <xmin>81.54</xmin>
            <ymin>352.82</ymin>
            <xmax>100.59</xmax>
            <ymax>380.94</ymax>
        </bndbox>
    </object>
    <object>
        <name>Char</name>
        <bndbox>
            <xmin>127.26</xmin>
            <ymin>352.3</ymin>
            <xmax>146.83</xmax>
            <ymax>382.78</ymax>
        </bndbox>
    </object>
    <object>
        <name>Char</name>
        <bndbox>
            <xmin>147.49</xmin>
            <ymin>357.95</ymin>
            <xmax>168.11</xmax>
            <ymax>383.96</ymax>
        </bndbox>
    </object>
    <object>
        <name>Char</name>
        <bndbox>
            <xmin>178.76</xmin>
            <ymin>350.72</ymin>
            <xmax>200.56</xmax>
            <ymax>382.64</ymax>
        </bndbox>
    </object>
    <object>
        <name>Char</name>
        <bndbox>
            <xmin>199.38</xmin>
            <ymin>332.72</ymin>
            <xmax>222.24</xmax>
            <ymax>385.8</ymax>
        </bndbox>
    </object>
    <object>
        <name>Char</name>
        <bndbox>
            <xmin>221.19</xmin>
            <ymin>355.58</ymin>
            <xmax>236.95</xmax>
            <ymax>385.14</ymax>
        </bndbox>
    </object>
    <object>
        <name>Char</name>
        <bndbox>
            <xmin>236.95</xmin>
            <ymin>331.54</ymin>
            <xmax>257.18</xmax>
            <ymax>380.15</ymax>
        </bndbox>
    </object>
    <object>
        <name>Char</name>
        <bndbox>
            <xmin>258.63</xmin>
            <ymin>348.88</ymin>
            <xmax>273.47</xmax>
            <ymax>384.09</ymax>
        </bndbox>
    </object>
    <object>
        <name>Char</name>
        <bndbox>
            <xmin>271.64</xmin>
            <ymin>352.43</ymin>
            <xmax>293.18</xmax>
            <ymax>382.51</ymax>
        </bndbox>
    </object>
    <object>
        <name>Char</name>
        <bndbox>
            <xmin>316.43</xmin>
            <ymin>366.75</ymin>
            <xmax>325.89</xmax>
            <ymax>389.87</ymax>
        </bndbox>
    </object>
    <object>
        <name>Char</name>
        <bndbox>
            <xmin>352.43</xmin>
            <ymin>335.48</ymin>
            <xmax>379.49</xmax>
            <ymax>382.91</ymax>
        </bndbox>
    </object>
    <object>
        <name>Char</name>
        <bndbox>
            <xmin>381.72</xmin>
            <ymin>346.52</ymin>
            <xmax>399.07</xmax>
            <ymax>384.35</ymax>
        </bndbox>
    </object>
    <object>
        <name>Char</name>
        <bndbox>
            <xmin>399.72</xmin>
            <ymin>351.11</ymin>
            <xmax>419.56</xmax>
            <ymax>381.2</ymax>
        </bndbox>
    </object>
    <object>
        <name>Char</name>
        <bndbox>
            <xmin>453.32</xmin>
            <ymin>350.85</ymin>
            <xmax>469.87</xmax>
            <ymax>381.46</ymax>
        </bndbox>
    </object>
    <object>
        <name>Char</name>
        <bndbox>
            <xmin>474.47</xmin>
            <ymin>337.45</ymin>
            <xmax>487.48</xmax>
            <ymax>376.99</ymax>
        </bndbox>
    </object>
    <object>
        <name>Char</name>
        <bndbox>
            <xmin>487.08</xmin>
            <ymin>346.65</ymin>
            <xmax>506.79</xmax>
            <ymax>378.7</ymax>
        </bndbox>
    </object>
    <object>
        <name>Char</name>
        <bndbox>
            <xmin>538.32</xmin>
            <ymin>325.37</ymin>
            <xmax>562.23</xmax>
            <ymax>380.54</ymax>
        </bndbox>
    </object>
    <object>
        <name>Char</name>
        <bndbox>
            <xmin>561.57</xmin>
            <ymin>342.18</ymin>
            <xmax>581.93</xmax>
            <ymax>380.67</ymax>
        </bndbox>
    </object>
    <object>
        <name>Char</name>
        <bndbox>
            <xmin>586.27</xmin>
            <ymin>324.58</ymin>
            <xmax>603.74</xmax>
            <ymax>376.21</ymax>
        </bndbox>
    </object>
    <object>
        <name>Char</name>
        <bndbox>
            <xmin>605.32</xmin>
            <ymin>352.43</ymin>
            <xmax>622.13</xmax>
            <ymax>378.31</ymax>
        </bndbox>
    </object>
    <object>
        <name>Char</name>
        <bndbox>
            <xmin>620.69</xmin>
            <ymin>349.41</ymin>
            <xmax>641.18</xmax>
            <ymax>380.8</ymax>
        </bndbox>
    </object>
    <object>
        <name>Char</name>
        <bndbox>
            <xmin>643.02</xmin>
            <ymin>349.67</ymin>
            <xmax>663.52</xmax>
            <ymax>440.05</ymax>
        </bndbox>
    </object>
    <object>
        <name>Char</name>
        <bndbox>
            <xmin>663.12</xmin>
            <ymin>347.31</ymin>
            <xmax>679.41</xmax>
            <ymax>379.1</ymax>
        </bndbox>
    </object>
    <object>
        <name>Char</name>
        <bndbox>
            <xmin>679.94</xmin>
            <ymin>346.25</ymin>
            <xmax>701.61</xmax>
            <ymax>379.1</ymax>
        </bndbox>
    </object>
    <object>
        <name>Char</name>
        <bndbox>
            <xmin>739.76</xmin>
            <ymin>331.89</ymin>
            <xmax>760.8</xmax>
            <ymax>379.61</ymax>
        </bndbox>
    </object>
    <object>
        <name>Char</name>
        <bndbox>
            <xmin>763.35</xmin>
            <ymin>350.52</ymin>
            <xmax>786.13</xmax>
            <ymax>378.94</ymax>
        </bndbox>
    </object>
    <object>
        <name>Char</name>
        <bndbox>
            <xmin>785.46</xmin>
            <ymin>327.73</ymin>
            <xmax>808.12</xmax>
            <ymax>380.68</ymax>
        </bndbox>
    </object>
    <object>
        <name>Char</name>
        <bndbox>
            <xmin>816.56</xmin>
            <ymin>364.73</ymin>
            <xmax>826.21</xmax>
            <ymax>380.68</ymax>
        </bndbox>
    </object>
    <object>
        <name>Char</name>
        <bndbox>
            <xmin>11.16</xmin>
            <ymin>438.42</ymin>
            <xmax>35.53</xmax>
            <ymax>496.3</ymax>
        </bndbox>
    </object>
    <object>
        <name>Char</name>
        <bndbox>
            <xmin>38.78</xmin>
            <ymin>465.02</ymin>
            <xmax>67.62</xmax>
            <ymax>499.14</ymax>
        </bndbox>
    </object>
    <object>
        <name>Char</name>
        <bndbox>
            <xmin>92.8</xmin>
            <ymin>458.12</ymin>
            <xmax>110.67</xmax>
            <ymax>497.72</ymax>
        </bndbox>
    </object>
    <object>
        <name>Char</name>
        <bndbox>
            <xmin>125.09</xmin>
            <ymin>456.09</ymin>
            <xmax>134.43</xmax>
            <ymax>498.74</ymax>
        </bndbox>
    </object>
    <object>
        <name>Char</name>
        <bndbox>
            <xmin>136.46</xmin>
            <ymin>463.6</ymin>
            <xmax>154.13</xmax>
            <ymax>500.77</ymax>
        </bndbox>
    </object>
    <object>
        <name>Char</name>
        <bndbox>
            <xmin>187.64</xmin>
            <ymin>461.16</ymin>
            <xmax>205.92</xmax>
            <ymax>493.66</ymax>
        </bndbox>
    </object>
    <object>
        <name>Char</name>
        <bndbox>
            <xmin>208.15</xmin>
            <ymin>465.83</ymin>
            <xmax>238.21</xmax>
            <ymax>497.52</ymax>
        </bndbox>
    </object>
    <object>
        <name>Char</name>
        <bndbox>
            <xmin>239.43</xmin>
            <ymin>467.46</ymin>
            <xmax>254.26</xmax>
            <ymax>499.75</ymax>
        </bndbox>
    </object>
    <object>
        <name>Char</name>
        <bndbox>
            <xmin>254.46</xmin>
            <ymin>460.15</ymin>
            <xmax>269.08</xmax>
            <ymax>498.74</ymax>
        </bndbox>
    </object>
    <object>
        <name>Char</name>
        <bndbox>
            <xmin>301.78</xmin>
            <ymin>449.18</ymin>
            <xmax>327.98</xmax>
            <ymax>496.09</ymax>
        </bndbox>
    </object>
    <object>
        <name>Char</name>
        <bndbox>
            <xmin>329.2</xmin>
            <ymin>458.93</ymin>
            <xmax>339.15</xmax>
            <ymax>498.13</ymax>
        </bndbox>
    </object>
    <object>
        <name>Char</name>
        <bndbox>
            <xmin>341.79</xmin>
            <ymin>468.27</ymin>
            <xmax>363.52</xmax>
            <ymax>504.83</ymax>
        </bndbox>
    </object>
    <object>
        <name>Char</name>
        <bndbox>
            <xmin>369.61</xmin>
            <ymin>461.16</ymin>
            <xmax>389.31</xmax>
            <ymax>497.52</ymax>
        </bndbox>
    </object>
    <object>
        <name>Char</name>
        <bndbox>
            <xmin>389.72</xmin>
            <ymin>467.46</ymin>
            <xmax>410.84</xmax>
            <ymax>497.72</ymax>
        </bndbox>
    </object>
    <object>
        <name>Char</name>
        <bndbox>
            <xmin>407.99</xmin>
            <ymin>469.69</ymin>
            <xmax>425.05</xmax>
            <ymax>498.13</ymax>
        </bndbox>
    </object>
    <object>
        <name>Char</name>
        <bndbox>
            <xmin>462.02</xmin>
            <ymin>452.43</ymin>
            <xmax>480.7</xmax>
            <ymax>492.85</ymax>
        </bndbox>
    </object>
    <object>
        <name>Char</name>
        <bndbox>
            <xmin>483.14</xmin>
            <ymin>467.05</ymin>
            <xmax>500.6</xmax>
            <ymax>497.11</ymax>
        </bndbox>
    </object>
    <object>
        <name>Char</name>
        <bndbox>
            <xmin>505.07</xmin>
            <ymin>445.93</ymin>
            <xmax>525.99</xmax>
            <ymax>503.41</ymax>
        </bndbox>
    </object>
    <object>
        <name>Char</name>
        <bndbox>
            <xmin>555.44</xmin>
            <ymin>446.74</ymin>
            <xmax>580.21</xmax>
            <ymax>499.34</ymax>
        </bndbox>
    </object>
    <object>
        <name>Char</name>
        <bndbox>
            <xmin>586.1</xmin>
            <ymin>470.71</ymin>
            <xmax>609.05</xmax>
            <ymax>500.77</ymax>
        </bndbox>
    </object>
    <object>
        <name>Char</name>
        <bndbox>
            <xmin>609.46</xmin>
            <ymin>442.07</ymin>
            <xmax>630.58</xmax>
            <ymax>496.09</ymax>
        </bndbox>
    </object>
    <object>
        <name>Char</name>
        <bndbox>
            <xmin>629.77</xmin>
            <ymin>466.85</ymin>
            <xmax>650.28</xmax>
            <ymax>497.52</ymax>
        </bndbox>
    </object>
    <object>
        <name>Char</name>
        <bndbox>
            <xmin>651.9</xmin>
            <ymin>467.66</ymin>
            <xmax>677.09</xmax>
            <ymax>496.5</ymax>
        </bndbox>
    </object>
    <object>
        <name>Char</name>
        <bndbox>
            <xmin>694.15</xmin>
            <ymin>463.8</ymin>
            <xmax>722.17</xmax>
            <ymax>497.11</ymax>
        </bndbox>
    </object>
    <object>
        <name>Char</name>
        <bndbox>
            <xmin>720.55</xmin>
            <ymin>445.53</ymin>
            <xmax>743.29</xmax>
            <ymax>497.11</ymax>
        </bndbox>
    </object>
    <object>
        <name>Char</name>
        <bndbox>
            <xmin>746.75</xmin>
            <ymin>444.92</ymin>
            <xmax>771.12</xmax>
            <ymax>496.5</ymax>
        </bndbox>
    </object>
    <object>
        <name>Char</name>
        <bndbox>
            <xmin>772.34</xmin>
            <ymin>444.71</ymin>
            <xmax>784.72</xmax>
            <ymax>494.67</ymax>
        </bndbox>
    </object>
    <object>
        <name>Char</name>
        <bndbox>
            <xmin>779.04</xmin>
            <ymin>449.38</ymin>
            <xmax>797.11</xmax>
            <ymax>499.14</ymax>
        </bndbox>
    </object>
</annotation>
