<?xml version="1.0" ?>
<annotation>
    <filename>1122.jpg</filename>
    <size>
        <width>832</width>
        <height>832</height>
        <depth>3</depth>
    </size>
    <object>
        <name>Char</name>
        <bndbox>
            <xmin>10.38</xmin>
            <ymin>371.55</ymin>
            <xmax>47.34</xmax>
            <ymax>473.72</ymax>
        </bndbox>
    </object>
    <object>
        <name>Char</name>
        <bndbox>
            <xmin>30.4</xmin>
            <ymin>384.9</ymin>
            <xmax>63.09</xmax>
            <ymax>443.43</ymax>
        </bndbox>
    </object>
    <object>
        <name>Char</name>
        <bndbox>
            <xmin>60.86</xmin>
            <ymin>412.63</ymin>
            <xmax>89.1</xmax>
            <ymax>469.62</ymax>
        </bndbox>
    </object>
    <object>
        <name>Char</name>
        <bndbox>
            <xmin>90.3</xmin>
            <ymin>392.09</ymin>
            <xmax>114.43</xmax>
            <ymax>439.84</ymax>
        </bndbox>
    </object>
    <object>
        <name>Char</name>
        <bndbox>
            <xmin>127.61</xmin>
            <ymin>388.5</ymin>
            <xmax>145.23</xmax>
            <ymax>428.88</ymax>
        </bndbox>
    </object>
    <object>
        <name>Char</name>
        <bndbox>
            <xmin>144.89</xmin>
            <ymin>417.76</ymin>
            <xmax>162.69</xmax>
            <ymax>453.02</ymax>
        </bndbox>
    </object>
    <object>
        <name>Char</name>
        <bndbox>
            <xmin>161.66</xmin>
            <ymin>396.88</ymin>
            <xmax>197.43</xmax>
            <ymax>452.67</ymax>
        </bndbox>
    </object>
    <object>
        <name>Char</name>
        <bndbox>
            <xmin>201.37</xmin>
            <ymin>417.42</ymin>
            <xmax>218.65</xmax>
            <ymax>454.9</ymax>
        </bndbox>
    </object>
    <object>
        <name>Char</name>
        <bndbox>
            <xmin>218.48</xmin>
            <ymin>383.53</ymin>
            <xmax>238.16</xmax>
            <ymax>444.12</ymax>
        </bndbox>
    </object>
    <object>
        <name>Char</name>
        <bndbox>
            <xmin>238.33</xmin>
            <ymin>415.19</ymin>
            <xmax>259.21</xmax>
            <ymax>455.75</ymax>
        </bndbox>
    </object>
    <object>
        <name>Char</name>
        <bndbox>
            <xmin>253.22</xmin>
            <ymin>374.12</ymin>
            <xmax>291.73</xmax>
            <ymax>472.87</ymax>
        </bndbox>
    </object>
    <object>
        <name>Char</name>
        <bndbox>
            <xmin>302.85</xmin>
            <ymin>356.15</ymin>
            <xmax>326.64</xmax>
            <ymax>403.38</ymax>
        </bndbox>
    </object>
    <object>
        <name>Char</name>
        <bndbox>
            <xmin>327.67</xmin>
            <ymin>369.84</ymin>
            <xmax>348.55</xmax>
            <ymax>385.23</ymax>
        </bndbox>
    </object>
    <object>
        <name>Char</name>
        <bndbox>
            <xmin>354.71</xmin>
            <ymin>400.65</ymin>
            <xmax>376.62</xmax>
            <ymax>432.82</ymax>
        </bndbox>
    </object>
    <object>
        <name>Char</name>
        <bndbox>
            <xmin>394.93</xmin>
            <ymin>397.39</ymin>
            <xmax>411.19</xmax>
            <ymax>440.18</ymax>
        </bndbox>
    </object>
    <object>
        <name>Char</name>
        <bndbox>
            <xmin>409.47</xmin>
            <ymin>389.35</ymin>
            <xmax>435.49</xmax>
            <ymax>402.7</ymax>
        </bndbox>
    </object>
    <object>
        <name>Char</name>
        <bndbox>
            <xmin>447.64</xmin>
            <ymin>397.91</ymin>
            <xmax>501.89</xmax>
            <ymax>447.71</ymax>
        </bndbox>
    </object>
    <object>
        <name>Char</name>
        <bndbox>
            <xmin>520.37</xmin>
            <ymin>383.02</ymin>
            <xmax>560.93</xmax>
            <ymax>444.12</ymax>
        </bndbox>
    </object>
    <object>
        <name>Char</name>
        <bndbox>
            <xmin>555.46</xmin>
            <ymin>410.74</ymin>
            <xmax>579.25</xmax>
            <ymax>490.84</ymax>
        </bndbox>
    </object>
    <object>
        <name>Char</name>
        <bndbox>
            <xmin>593.45</xmin>
            <ymin>392.43</ymin>
            <xmax>607.14</xmax>
            <ymax>432.48</ymax>
        </bndbox>
    </object>
    <object>
        <name>Char</name>
        <bndbox>
            <xmin>610.05</xmin>
            <ymin>389.86</ymin>
            <xmax>647.19</xmax>
            <ymax>445.83</ymax>
        </bndbox>
    </object>
    <object>
        <name>Char</name>
        <bndbox>
            <xmin>660.37</xmin>
            <ymin>408.52</ymin>
            <xmax>678.16</xmax>
            <ymax>437.27</ymax>
        </bndbox>
    </object>
    <object>
        <name>Char</name>
        <bndbox>
            <xmin>679.36</xmin>
            <ymin>394.31</ymin>
            <xmax>701.78</xmax>
            <ymax>439.32</ymax>
        </bndbox>
    </object>
    <object>
        <name>Char</name>
        <bndbox>
            <xmin>702.47</xmin>
            <ymin>402.19</ymin>
            <xmax>728.48</xmax>
            <ymax>439.15</ymax>
        </bndbox>
    </object>
    <object>
        <name>Char</name>
        <bndbox>
            <xmin>724.89</xmin>
            <ymin>413.31</ymin>
            <xmax>740.8</xmax>
            <ymax>447.71</ymax>
        </bndbox>
    </object>
    <object>
        <name>Char</name>
        <bndbox>
            <xmin>740.8</xmin>
            <ymin>396.71</ymin>
            <xmax>771.44</xmax>
            <ymax>438.47</ymax>
        </bndbox>
    </object>
    <object>
        <name>Char</name>
        <bndbox>
            <xmin>774.17</xmin>
            <ymin>415.88</ymin>
            <xmax>793</xmax>
            <ymax>456.61</ymax>
        </bndbox>
    </object>
    <object>
        <name>Char</name>
        <bndbox>
            <xmin>782.9</xmin>
            <ymin>381.99</ymin>
            <xmax>803.44</xmax>
            <ymax>418.79</ymax>
        </bndbox>
    </object>
    <object>
        <name>Char</name>
        <bndbox>
            <xmin>804.98</xmin>
            <ymin>391.23</ymin>
            <xmax>823.63</xmax>
            <ymax>409.03</ymax>
        </bndbox>
    </object>
</annotation>
