<?xml version="1.0" ?>
<annotation>
    <filename>1213.jpg</filename>
    <size>
        <width>832</width>
        <height>832</height>
        <depth>3</depth>
    </size>
    <object>
        <name>Char</name>
        <bndbox>
            <xmin>41.42</xmin>
            <ymin>398.67</ymin>
            <xmax>84.28</xmax>
            <ymax>435.92</ymax>
        </bndbox>
    </object>
    <object>
        <name>Char</name>
        <bndbox>
            <xmin>97.88</xmin>
            <ymin>396.9</ymin>
            <xmax>139.85</xmax>
            <ymax>437.98</ymax>
        </bndbox>
    </object>
    <object>
        <name>Char</name>
        <bndbox>
            <xmin>167.93</xmin>
            <ymin>326.84</ymin>
            <xmax>222.91</xmax>
            <ymax>392.76</ymax>
        </bndbox>
    </object>
    <object>
        <name>Char</name>
        <bndbox>
            <xmin>166.45</xmin>
            <ymin>386.26</ymin>
            <xmax>216.11</xmax>
            <ymax>437.39</ymax>
        </bndbox>
    </object>
    <object>
        <name>Char</name>
        <bndbox>
            <xmin>163.5</xmin>
            <ymin>448.33</ymin>
            <xmax>205.17</xmax>
            <ymax>497.1</ymax>
        </bndbox>
    </object>
    <object>
        <name>Char</name>
        <bndbox>
            <xmin>212.27</xmin>
            <ymin>323</ymin>
            <xmax>242.71</xmax>
            <ymax>500.94</ymax>
        </bndbox>
    </object>
    <object>
        <name>Char</name>
        <bndbox>
            <xmin>142.51</xmin>
            <ymin>323.59</ymin>
            <xmax>174.14</xmax>
            <ymax>501.83</ymax>
        </bndbox>
    </object>
    <object>
        <name>Char</name>
        <bndbox>
            <xmin>284.69</xmin>
            <ymin>391.58</ymin>
            <xmax>326.36</xmax>
            <ymax>441.24</ymax>
        </bndbox>
    </object>
    <object>
        <name>Char</name>
        <bndbox>
            <xmin>344.1</xmin>
            <ymin>398.38</ymin>
            <xmax>380.46</xmax>
            <ymax>448.63</ymax>
        </bndbox>
    </object>
    <object>
        <name>Char</name>
        <bndbox>
            <xmin>406.47</xmin>
            <ymin>328.91</ymin>
            <xmax>456.42</xmax>
            <ymax>384.78</ymax>
        </bndbox>
    </object>
    <object>
        <name>Char</name>
        <bndbox>
            <xmin>429.52</xmin>
            <ymin>390.99</ymin>
            <xmax>457.31</xmax>
            <ymax>445.37</ymax>
        </bndbox>
    </object>
    <object>
        <name>Char</name>
        <bndbox>
            <xmin>400.26</xmin>
            <ymin>410.49</ymin>
            <xmax>432.18</xmax>
            <ymax>436.21</ymax>
        </bndbox>
    </object>
    <object>
        <name>Char</name>
        <bndbox>
            <xmin>398.49</xmin>
            <ymin>465.77</ymin>
            <xmax>425.09</xmax>
            <ymax>488.23</ymax>
        </bndbox>
    </object>
    <object>
        <name>Char</name>
        <bndbox>
            <xmin>420.36</xmin>
            <ymin>451.29</ymin>
            <xmax>454.65</xmax>
            <ymax>500.65</ymax>
        </bndbox>
    </object>
    <object>
        <name>Char</name>
        <bndbox>
            <xmin>452.28</xmin>
            <ymin>320.34</ymin>
            <xmax>494.26</xmax>
            <ymax>497.99</ymax>
        </bndbox>
    </object>
    <object>
        <name>Char</name>
        <bndbox>
            <xmin>379.27</xmin>
            <ymin>336.6</ymin>
            <xmax>413.56</xmax>
            <ymax>474.64</ymax>
        </bndbox>
    </object>
    <object>
        <name>Char</name>
        <bndbox>
            <xmin>515.24</xmin>
            <ymin>390.1</ymin>
            <xmax>557.81</xmax>
            <ymax>432.96</ymax>
        </bndbox>
    </object>
    <object>
        <name>Char</name>
        <bndbox>
            <xmin>572.88</xmin>
            <ymin>381.82</ymin>
            <xmax>613.67</xmax>
            <ymax>440.35</ymax>
        </bndbox>
    </object>
    <object>
        <name>Char</name>
        <bndbox>
            <xmin>679.59</xmin>
            <ymin>441.83</ymin>
            <xmax>718.9</xmax>
            <ymax>504.2</ymax>
        </bndbox>
    </object>
    <object>
        <name>Char</name>
        <bndbox>
            <xmin>673.68</xmin>
            <ymin>387.73</ymin>
            <xmax>729.54</xmax>
            <ymax>446.26</ymax>
        </bndbox>
    </object>
    <object>
        <name>Char</name>
        <bndbox>
            <xmin>694.66</xmin>
            <ymin>366.16</ymin>
            <xmax>718.31</xmax>
            <ymax>400.15</ymax>
        </bndbox>
    </object>
    <object>
        <name>Char</name>
        <bndbox>
            <xmin>660.67</xmin>
            <ymin>330.39</ymin>
            <xmax>708.56</xmax>
            <ymax>383.6</ymax>
        </bndbox>
    </object>
    <object>
        <name>Char</name>
        <bndbox>
            <xmin>720.97</xmin>
            <ymin>325.96</ymin>
            <xmax>754.67</xmax>
            <ymax>380.05</ymax>
        </bndbox>
    </object>
    <object>
        <name>Char</name>
        <bndbox>
            <xmin>754.37</xmin>
            <ymin>308.22</ymin>
            <xmax>783.93</xmax>
            <ymax>488.53</ymax>
        </bndbox>
    </object>
    <object>
        <name>Char</name>
        <bndbox>
            <xmin>629.34</xmin>
            <ymin>315.91</ymin>
            <xmax>665.7</xmax>
            <ymax>500.35</ymax>
        </bndbox>
    </object>
</annotation>
