<?xml version="1.0" ?>
<annotation>
    <filename>1238.jpg</filename>
    <size>
        <width>832</width>
        <height>832</height>
        <depth>3</depth>
    </size>
    <object>
        <name>Char</name>
        <bndbox>
            <xmin>188.73</xmin>
            <ymin>367.75</ymin>
            <xmax>231</xmax>
            <ymax>430.11</ymax>
        </bndbox>
    </object>
    <object>
        <name>Char</name>
        <bndbox>
            <xmin>264.99</xmin>
            <ymin>397.6</ymin>
            <xmax>311.7</xmax>
            <ymax>424.79</ymax>
        </bndbox>
    </object>
    <object>
        <name>Char</name>
        <bndbox>
            <xmin>369.04</xmin>
            <ymin>377.8</ymin>
            <xmax>417.51</xmax>
            <ymax>438.1</ymax>
        </bndbox>
    </object>
    <object>
        <name>Char</name>
        <bndbox>
            <xmin>409.83</xmin>
            <ymin>411.2</ymin>
            <xmax>437.32</xmax>
            <ymax>440.76</ymax>
        </bndbox>
    </object>
    <object>
        <name>Char</name>
        <bndbox>
            <xmin>488.46</xmin>
            <ymin>396.12</ymin>
            <xmax>532.5</xmax>
            <ymax>425.98</ymax>
        </bndbox>
    </object>
    <object>
        <name>Char</name>
        <bndbox>
            <xmin>555.85</xmin>
            <ymin>384.89</ymin>
            <xmax>599.3</xmax>
            <ymax>432.18</ymax>
        </bndbox>
    </object>
    <object>
        <name>Char</name>
        <bndbox>
            <xmin>576.24</xmin>
            <ymin>415.04</ymin>
            <xmax>615.26</xmax>
            <ymax>450.81</ymax>
        </bndbox>
    </object>
</annotation>
