<?xml version="1.0" ?>
<annotation>
    <filename>1303.jpg</filename>
    <size>
        <width>832</width>
        <height>832</height>
        <depth>3</depth>
    </size>
    <object>
        <name>Char</name>
        <bndbox>
            <xmin>8.74</xmin>
            <ymin>306.64</ymin>
            <xmax>30.16</xmax>
            <ymax>359.97</ymax>
        </bndbox>
    </object>
    <object>
        <name>Char</name>
        <bndbox>
            <xmin>33.7</xmin>
            <ymin>309.53</ymin>
            <xmax>53.8</xmax>
            <ymax>360.24</ymax>
        </bndbox>
    </object>
    <object>
        <name>Char</name>
        <bndbox>
            <xmin>55.91</xmin>
            <ymin>336.33</ymin>
            <xmax>74.3</xmax>
            <ymax>363.65</ymax>
        </bndbox>
    </object>
    <object>
        <name>Char</name>
        <bndbox>
            <xmin>119.75</xmin>
            <ymin>320.43</ymin>
            <xmax>140.77</xmax>
            <ymax>361.42</ymax>
        </bndbox>
    </object>
    <object>
        <name>Char</name>
        <bndbox>
            <xmin>143.53</xmin>
            <ymin>322.93</ymin>
            <xmax>154.7</xmax>
            <ymax>364.57</ymax>
        </bndbox>
    </object>
    <object>
        <name>Char</name>
        <bndbox>
            <xmin>156.67</xmin>
            <ymin>332.12</ymin>
            <xmax>170.46</xmax>
            <ymax>361.03</ymax>
        </bndbox>
    </object>
    <object>
        <name>Char</name>
        <bndbox>
            <xmin>214.47</xmin>
            <ymin>310.97</ymin>
            <xmax>235.23</xmax>
            <ymax>363</ymax>
        </bndbox>
    </object>
    <object>
        <name>Char</name>
        <bndbox>
            <xmin>236.02</xmin>
            <ymin>333.04</ymin>
            <xmax>255.33</xmax>
            <ymax>360.5</ymax>
        </bndbox>
    </object>
    <object>
        <name>Char</name>
        <bndbox>
            <xmin>255.07</xmin>
            <ymin>329.1</ymin>
            <xmax>268.07</xmax>
            <ymax>358.4</ymax>
        </bndbox>
    </object>
    <object>
        <name>Char</name>
        <bndbox>
            <xmin>267.94</xmin>
            <ymin>332.12</ymin>
            <xmax>285.15</xmax>
            <ymax>361.81</ymax>
        </bndbox>
    </object>
    <object>
        <name>Char</name>
        <bndbox>
            <xmin>284.36</xmin>
            <ymin>306.51</ymin>
            <xmax>304.07</xmax>
            <ymax>367.99</ymax>
        </bndbox>
    </object>
    <object>
        <name>Char</name>
        <bndbox>
            <xmin>308.8</xmin>
            <ymin>336.46</ymin>
            <xmax>326.01</xmax>
            <ymax>361.03</ymax>
        </bndbox>
    </object>
    <object>
        <name>Char</name>
        <bndbox>
            <xmin>326.14</xmin>
            <ymin>334.75</ymin>
            <xmax>342.56</xmax>
            <ymax>361.55</ymax>
        </bndbox>
    </object>
    <object>
        <name>Char</name>
        <bndbox>
            <xmin>344.79</xmin>
            <ymin>317.41</ymin>
            <xmax>354.91</xmax>
            <ymax>361.42</ymax>
        </bndbox>
    </object>
    <object>
        <name>Char</name>
        <bndbox>
            <xmin>360.03</xmin>
            <ymin>308.87</ymin>
            <xmax>375.4</xmax>
            <ymax>361.29</ymax>
        </bndbox>
    </object>
    <object>
        <name>Char</name>
        <bndbox>
            <xmin>376.58</xmin>
            <ymin>336.98</ymin>
            <xmax>396.29</xmax>
            <ymax>362.47</ymax>
        </bndbox>
    </object>
    <object>
        <name>Char</name>
        <bndbox>
            <xmin>400.36</xmin>
            <ymin>333.04</ymin>
            <xmax>420.2</xmax>
            <ymax>363.52</ymax>
        </bndbox>
    </object>
    <object>
        <name>Char</name>
        <bndbox>
            <xmin>421.78</xmin>
            <ymin>332.65</ymin>
            <xmax>444.24</xmax>
            <ymax>416.86</ymax>
        </bndbox>
    </object>
    <object>
        <name>Char</name>
        <bndbox>
            <xmin>484.83</xmin>
            <ymin>330.28</ymin>
            <xmax>500.73</xmax>
            <ymax>359.71</ymax>
        </bndbox>
    </object>
    <object>
        <name>Char</name>
        <bndbox>
            <xmin>500.73</xmin>
            <ymin>334.75</ymin>
            <xmax>515.05</xmax>
            <ymax>363</ymax>
        </bndbox>
    </object>
    <object>
        <name>Char</name>
        <bndbox>
            <xmin>517.94</xmin>
            <ymin>333.44</ymin>
            <xmax>533.57</xmax>
            <ymax>366.41</ymax>
        </bndbox>
    </object>
    <object>
        <name>Char</name>
        <bndbox>
            <xmin>560.5</xmin>
            <ymin>319.12</ymin>
            <xmax>581.79</xmax>
            <ymax>362.73</ymax>
        </bndbox>
    </object>
    <object>
        <name>Char</name>
        <bndbox>
            <xmin>578.77</xmin>
            <ymin>338.69</ymin>
            <xmax>595.32</xmax>
            <ymax>360.76</ymax>
        </bndbox>
    </object>
    <object>
        <name>Char</name>
        <bndbox>
            <xmin>595.06</xmin>
            <ymin>318.99</ymin>
            <xmax>610.16</xmax>
            <ymax>366.67</ymax>
        </bndbox>
    </object>
    <object>
        <name>Char</name>
        <bndbox>
            <xmin>611.61</xmin>
            <ymin>318.99</ymin>
            <xmax>624.75</xmax>
            <ymax>364.05</ymax>
        </bndbox>
    </object>
    <object>
        <name>Char</name>
        <bndbox>
            <xmin>620.94</xmin>
            <ymin>336.46</ymin>
            <xmax>634.6</xmax>
            <ymax>361.55</ymax>
        </bndbox>
    </object>
    <object>
        <name>Char</name>
        <bndbox>
            <xmin>635.65</xmin>
            <ymin>340.4</ymin>
            <xmax>649.31</xmax>
            <ymax>362.6</ymax>
        </bndbox>
    </object>
    <object>
        <name>Char</name>
        <bndbox>
            <xmin>657.33</xmin>
            <ymin>317.94</ymin>
            <xmax>675.32</xmax>
            <ymax>378.5</ymax>
        </bndbox>
    </object>
    <object>
        <name>Char</name>
        <bndbox>
            <xmin>672.3</xmin>
            <ymin>339.22</ymin>
            <xmax>683.6</xmax>
            <ymax>359.45</ymax>
        </bndbox>
    </object>
    <object>
        <name>Char</name>
        <bndbox>
            <xmin>684.13</xmin>
            <ymin>317.8</ymin>
            <xmax>694.63</xmax>
            <ymax>358.4</ymax>
        </bndbox>
    </object>
    <object>
        <name>Char</name>
        <bndbox>
            <xmin>692.01</xmin>
            <ymin>336.59</ymin>
            <xmax>707.64</xmax>
            <ymax>398.73</ymax>
        </bndbox>
    </object>
    <object>
        <name>Char</name>
        <bndbox>
            <xmin>707.77</xmin>
            <ymin>335.01</ymin>
            <xmax>720.12</xmax>
            <ymax>360.11</ymax>
        </bndbox>
    </object>
    <object>
        <name>Char</name>
        <bndbox>
            <xmin>719.6</xmin>
            <ymin>334.36</ymin>
            <xmax>737.33</xmax>
            <ymax>361.03</ymax>
        </bndbox>
    </object>
    <object>
        <name>Char</name>
        <bndbox>
            <xmin>774.8</xmin>
            <ymin>331.67</ymin>
            <xmax>784.62</xmax>
            <ymax>355.15</ymax>
        </bndbox>
    </object>
    <object>
        <name>Char</name>
        <bndbox>
            <xmin>787.14</xmin>
            <ymin>318.13</ymin>
            <xmax>794.31</xmax>
            <ymax>359.53</ymax>
        </bndbox>
    </object>
    <object>
        <name>Char</name>
        <bndbox>
            <xmin>793.25</xmin>
            <ymin>334.85</ymin>
            <xmax>808.51</xmax>
            <ymax>360.46</ymax>
        </bndbox>
    </object>
    <object>
        <name>Char</name>
        <bndbox>
            <xmin>808.64</xmin>
            <ymin>316.54</ymin>
            <xmax>827.62</xmax>
            <ymax>360.2</ymax>
        </bndbox>
    </object>
    <object>
        <name>Char</name>
        <bndbox>
            <xmin>729.68</xmin>
            <ymin>426.41</ymin>
            <xmax>749.59</xmax>
            <ymax>482.15</ymax>
        </bndbox>
    </object>
    <object>
        <name>Char</name>
        <bndbox>
            <xmin>717.08</xmin>
            <ymin>452.29</ymin>
            <xmax>729.68</xmax>
            <ymax>477.37</ymax>
        </bndbox>
    </object>
    <object>
        <name>Char</name>
        <bndbox>
            <xmin>706.99</xmin>
            <ymin>437.69</ymin>
            <xmax>717.87</xmax>
            <ymax>478.7</ymax>
        </bndbox>
    </object>
    <object>
        <name>Char</name>
        <bndbox>
            <xmin>693.59</xmin>
            <ymin>430</ymin>
            <xmax>705.14</xmax>
            <ymax>477.64</ymax>
        </bndbox>
    </object>
    <object>
        <name>Char</name>
        <bndbox>
            <xmin>671.83</xmin>
            <ymin>451.36</ymin>
            <xmax>690.14</xmax>
            <ymax>520.5</ymax>
        </bndbox>
    </object>
    <object>
        <name>Char</name>
        <bndbox>
            <xmin>654.58</xmin>
            <ymin>451.1</ymin>
            <xmax>670.63</xmax>
            <ymax>478.96</ymax>
        </bndbox>
    </object>
    <object>
        <name>Char</name>
        <bndbox>
            <xmin>623.66</xmin>
            <ymin>451.1</ymin>
            <xmax>650.73</xmax>
            <ymax>480.69</ymax>
        </bndbox>
    </object>
    <object>
        <name>Char</name>
        <bndbox>
            <xmin>558.9</xmin>
            <ymin>454.41</ymin>
            <xmax>580</xmax>
            <ymax>528.86</ymax>
        </bndbox>
    </object>
    <object>
        <name>Char</name>
        <bndbox>
            <xmin>539.53</xmin>
            <ymin>452.29</ymin>
            <xmax>556.11</xmax>
            <ymax>479.76</ymax>
        </bndbox>
    </object>
    <object>
        <name>Char</name>
        <bndbox>
            <xmin>516.44</xmin>
            <ymin>457.33</ymin>
            <xmax>531.96</xmax>
            <ymax>482.15</ymax>
        </bndbox>
    </object>
    <object>
        <name>Char</name>
        <bndbox>
            <xmin>499.98</xmin>
            <ymin>435.44</ymin>
            <xmax>515.11</xmax>
            <ymax>479.89</ymax>
        </bndbox>
    </object>
    <object>
        <name>Char</name>
        <bndbox>
            <xmin>484.99</xmin>
            <ymin>434.64</ymin>
            <xmax>499.85</xmax>
            <ymax>478.83</ymax>
        </bndbox>
    </object>
    <object>
        <name>Char</name>
        <bndbox>
            <xmin>469.6</xmin>
            <ymin>452.29</ymin>
            <xmax>483.26</xmax>
            <ymax>480.42</ymax>
        </bndbox>
    </object>
    <object>
        <name>Char</name>
        <bndbox>
            <xmin>456.59</xmin>
            <ymin>431.32</ymin>
            <xmax>470.39</xmax>
            <ymax>478.17</ymax>
        </bndbox>
    </object>
    <object>
        <name>Char</name>
        <bndbox>
            <xmin>440.67</xmin>
            <ymin>453.22</ymin>
            <xmax>452.21</xmax>
            <ymax>479.49</ymax>
        </bndbox>
    </object>
    <object>
        <name>Char</name>
        <bndbox>
            <xmin>417.98</xmin>
            <ymin>455.47</ymin>
            <xmax>434.43</xmax>
            <ymax>481.35</ymax>
        </bndbox>
    </object>
    <object>
        <name>Char</name>
        <bndbox>
            <xmin>393.69</xmin>
            <ymin>455.34</ymin>
            <xmax>416.91</xmax>
            <ymax>481.35</ymax>
        </bndbox>
    </object>
    <object>
        <name>Char</name>
        <bndbox>
            <xmin>372.33</xmin>
            <ymin>423.89</ymin>
            <xmax>392.5</xmax>
            <ymax>476.84</ymax>
        </bndbox>
    </object>
    <object>
        <name>Char</name>
        <bndbox>
            <xmin>6.17</xmin>
            <ymin>447.78</ymin>
            <xmax>21.8</xmax>
            <ymax>475.83</ymax>
        </bndbox>
    </object>
    <object>
        <name>Char</name>
        <bndbox>
            <xmin>20.55</xmin>
            <ymin>453.64</ymin>
            <xmax>43.29</xmax>
            <ymax>479.6</ymax>
        </bndbox>
    </object>
    <object>
        <name>Char</name>
        <bndbox>
            <xmin>44.13</xmin>
            <ymin>451.41</ymin>
            <xmax>57.66</xmax>
            <ymax>478.06</ymax>
        </bndbox>
    </object>
    <object>
        <name>Char</name>
        <bndbox>
            <xmin>61.01</xmin>
            <ymin>438.57</ymin>
            <xmax>71.34</xmax>
            <ymax>478.9</ymax>
        </bndbox>
    </object>
    <object>
        <name>Char</name>
        <bndbox>
            <xmin>108.45</xmin>
            <ymin>424.9</ymin>
            <xmax>135.52</xmax>
            <ymax>480.43</ymax>
        </bndbox>
    </object>
    <object>
        <name>Char</name>
        <bndbox>
            <xmin>130.22</xmin>
            <ymin>456.85</ymin>
            <xmax>150.59</xmax>
            <ymax>479.74</ymax>
        </bndbox>
    </object>
    <object>
        <name>Char</name>
        <bndbox>
            <xmin>150.45</xmin>
            <ymin>427.27</ymin>
            <xmax>166.78</xmax>
            <ymax>479.6</ymax>
        </bndbox>
    </object>
    <object>
        <name>Char</name>
        <bndbox>
            <xmin>170.55</xmin>
            <ymin>454.48</ymin>
            <xmax>185.62</xmax>
            <ymax>482.39</ymax>
        </bndbox>
    </object>
    <object>
        <name>Char</name>
        <bndbox>
            <xmin>185.2</xmin>
            <ymin>453.78</ymin>
            <xmax>205.29</xmax>
            <ymax>481.69</ymax>
        </bndbox>
    </object>
    <object>
        <name>Char</name>
        <bndbox>
            <xmin>261.94</xmin>
            <ymin>426.57</ymin>
            <xmax>285.81</xmax>
            <ymax>479.04</ymax>
        </bndbox>
    </object>
    <object>
        <name>Char</name>
        <bndbox>
            <xmin>286.92</xmin>
            <ymin>448.06</ymin>
            <xmax>301.99</xmax>
            <ymax>476.11</ymax>
        </bndbox>
    </object>
    <object>
        <name>Char</name>
        <bndbox>
            <xmin>300.88</xmin>
            <ymin>455.88</ymin>
            <xmax>319.71</xmax>
            <ymax>481.13</ymax>
        </bndbox>
    </object>
</annotation>
