<?xml version="1.0" ?>
<annotation>
    <filename>1482.jpg</filename>
    <size>
        <width>832</width>
        <height>832</height>
        <depth>3</depth>
    </size>
    <object>
        <name>Char</name>
        <bndbox>
            <xmin>243</xmin>
            <ymin>377</ymin>
            <xmax>263</xmax>
            <ymax>432</ymax>
        </bndbox>
    </object>
    <object>
        <name>Char</name>
        <bndbox>
            <xmin>575</xmin>
            <ymin>437</ymin>
            <xmax>602</xmax>
            <ymax>465</ymax>
        </bndbox>
    </object>
    <object>
        <name>Char</name>
        <bndbox>
            <xmin>206</xmin>
            <ymin>373</ymin>
            <xmax>226</xmax>
            <ymax>404</ymax>
        </bndbox>
    </object>
    <object>
        <name>Char</name>
        <bndbox>
            <xmin>605</xmin>
            <ymin>438</ymin>
            <xmax>638</xmax>
            <ymax>496</ymax>
        </bndbox>
    </object>
    <object>
        <name>Char</name>
        <bndbox>
            <xmin>410</xmin>
            <ymin>379</ymin>
            <xmax>435</xmax>
            <ymax>402</ymax>
        </bndbox>
    </object>
    <object>
        <name>Char</name>
        <bndbox>
            <xmin>229</xmin>
            <ymin>370</ymin>
            <xmax>242</xmax>
            <ymax>404</ymax>
        </bndbox>
    </object>
    <object>
        <name>Char</name>
        <bndbox>
            <xmin>327</xmin>
            <ymin>375</ymin>
            <xmax>351</xmax>
            <ymax>403</ymax>
        </bndbox>
    </object>
    <object>
        <name>Char</name>
        <bndbox>
            <xmin>546</xmin>
            <ymin>421</ymin>
            <xmax>563</xmax>
            <ymax>459</ymax>
        </bndbox>
    </object>
    <object>
        <name>Char</name>
        <bndbox>
            <xmin>374</xmin>
            <ymin>436</ymin>
            <xmax>396</xmax>
            <ymax>463</ymax>
        </bndbox>
    </object>
    <object>
        <name>Char</name>
        <bndbox>
            <xmin>264</xmin>
            <ymin>379</ymin>
            <xmax>284</xmax>
            <ymax>404</ymax>
        </bndbox>
    </object>
    <object>
        <name>Char</name>
        <bndbox>
            <xmin>399</xmin>
            <ymin>424</ymin>
            <xmax>422</xmax>
            <ymax>462</ymax>
        </bndbox>
    </object>
    <object>
        <name>Char</name>
        <bndbox>
            <xmin>385</xmin>
            <ymin>367</ymin>
            <xmax>407</xmax>
            <ymax>402</ymax>
        </bndbox>
    </object>
    <object>
        <name>Char</name>
        <bndbox>
            <xmin>306</xmin>
            <ymin>417</ymin>
            <xmax>345</xmax>
            <ymax>461</ymax>
        </bndbox>
    </object>
    <object>
        <name>Char</name>
        <bndbox>
            <xmin>435</xmin>
            <ymin>380</ymin>
            <xmax>456</xmax>
            <ymax>403</ymax>
        </bndbox>
    </object>
    <object>
        <name>Char</name>
        <bndbox>
            <xmin>427</xmin>
            <ymin>430</ymin>
            <xmax>447</xmax>
            <ymax>459</ymax>
        </bndbox>
    </object>
    <object>
        <name>Char</name>
        <bndbox>
            <xmin>516.07</xmin>
            <ymin>419.59</ymin>
            <xmax>541.07</xmax>
            <ymax>459.59</ymax>
        </bndbox>
    </object>
    <object>
        <name>Char</name>
        <bndbox>
            <xmin>448</xmin>
            <ymin>436</ymin>
            <xmax>470</xmax>
            <ymax>463</ymax>
        </bndbox>
    </object>
    <object>
        <name>Char</name>
        <bndbox>
            <xmin>473.8</xmin>
            <ymin>438.23</ymin>
            <xmax>495.17</xmax>
            <ymax>462.9</ymax>
        </bndbox>
    </object>
    <object>
        <name>Char</name>
        <bndbox>
            <xmin>355</xmin>
            <ymin>378</ymin>
            <xmax>380</xmax>
            <ymax>403</ymax>
        </bndbox>
    </object>
    <object>
        <name>Char</name>
        <bndbox>
            <xmin>285</xmin>
            <ymin>367</ymin>
            <xmax>306</xmax>
            <ymax>402</ymax>
        </bndbox>
    </object>
    <object>
        <name>Char</name>
        <bndbox>
            <xmin>349</xmin>
            <ymin>429</ymin>
            <xmax>371</xmax>
            <ymax>462</ymax>
        </bndbox>
    </object>
    <object>
        <name>Char</name>
        <bndbox>
            <xmin>495.78</xmin>
            <ymin>440.36</ymin>
            <xmax>519.96</xmax>
            <ymax>464.54</ymax>
        </bndbox>
    </object>
</annotation>
